extractlib/__init__.py
extractlib/base_extract.py
extractlib/config_loader.py
extractlib/enums.py
extractlib-0.0.3.dist-info/LICENSE
extractlib-0.0.3.dist-info/METADATA
extractlib-0.0.3.dist-info/WHEEL
extractlib-0.0.3.dist-info/top_level.txt
extractlib-0.0.3.dist-info/RECORD
